model_transformer/__init__.py
model_transformer-0.2.0.dist-info/LICENSE
model_transformer-0.2.0.dist-info/METADATA
model_transformer-0.2.0.dist-info/WHEEL
model_transformer-0.2.0.dist-info/RECORD
