Metadata-Version: 2.1
Name: model-transformer
Version: 0.2.0
Summary: A small library aimed to help cleaning input json data, and allowing a more centered source of truth.
License: MIT
Author: Giancarlo Rocha
Author-email: giancarloiff@gmail.com
Requires-Python: >=3.8,<4.0
Classifier: License :: OSI Approved :: MIT License
Classifier: Programming Language :: Python :: 3
Classifier: Programming Language :: Python :: 3.8
Classifier: Programming Language :: Python :: 3.9
Classifier: Programming Language :: Python :: 3.10
Classifier: Programming Language :: Python :: 3.11
